{
  "generator-jhipster": {
    "promptValues": {
      "packageName": "fr.persee",
      "nativeLanguage": "fr"
    },
    "jhipsterVersion": "4.9.0",
    "baseName": "myappdocumentms",
    "packageName": "fr.persee",
    "packageFolder": "fr/persee",
    "serverPort": "8081",
    "authenticationType": "jwt",
    "hibernateCache": "hazelcast",
    "clusteredHttpSession": false,
    "websocket": false,
    "databaseType": "sql",
    "devDatabaseType": "postgresql",
    "prodDatabaseType": "postgresql",
    "searchEngine": false,
    "messageBroker": false,
    "serviceDiscoveryType": "eureka",
    "buildTool": "maven",
    "enableSocialSignIn": false,
    "enableSwaggerCodegen": false,
    "jwtSecretKey": "ea8e27cc44b18f1995fc988fcae9238856c5827d",
    "enableTranslation": true,
    "applicationType": "microservice",
    "testFrameworks": [],
    "jhiPrefix": "jhi",
    "skipClient": true,
    "skipUserManagement": true,
    "nativeLanguage": "fr",
    "languages": [
      "fr",
      "en"
    ],
    "clientPackageManager": "yarn"
  }
}